django_editorjs/__init__.py
django_editorjs/fields.py
django_editorjs/static/django-editorjs.css
django_editorjs/static/django-editorjs.js
django_editorjs/templates/editorjs.html
django_editorjs/widgets.py
django_editorjs-0.2.0.dist-info/WHEEL
django_editorjs-0.2.0.dist-info/METADATA
django_editorjs-0.2.0.dist-info/RECORD
