Metadata-Version: 2.1
Name: django-editorjs
Version: 0.2.0
Summary: Django plugin for using Editor.js in admin
Home-page: https://github.com/VLZH/django-editorjs
Author: vlzh
Author-email: vlzh@pm.me
Requires-Python: >=3.4,<4.0
Classifier: Programming Language :: Python :: 3
Classifier: Programming Language :: Python :: 3.4
Classifier: Programming Language :: Python :: 3.5
Classifier: Programming Language :: Python :: 3.6
Classifier: Programming Language :: Python :: 3.7
Classifier: Programming Language :: Python :: 3.8
Project-URL: Documentation, https://github.com/VLZH/django-editorjs
Project-URL: Repository, https://github.com/VLZH/django-editorjs
